[{"id":10015,"title":"Blender-like flow editor for Neural Networks"},{"id":10014,"title":"Inverse Kinematics algorithms — WebGL"},{"id":10013,"title":"WebGL painterly rendering"},{"id":10012,"title":"WebGL for light-speed prototyping: Minecraft with Portals"},{"id":10011,"title":"WebGL Gerstner waves"},{"id":10010,"title":"Approximate Shadow Volume for smooth geometry"},{"id":10009,"title":"First-person mobile controls for Three.js"},{"id":10008,"title":"Real-time Wormhole effect"},{"id":10007,"title":"Image reconstruction with primitives"},{"id":10006,"title":"Persistent homology on an example"},{"id":10005,"title":"Peg rectangle self-intersecting surface"},{"id":10004,"title":"Persistence Wasserstein solver"},{"id":10003,"title":"Particle tracing for vector fields"},{"id":10002,"title":"Lightspeed Japanese vocabulary learning"},{"id":10001,"title":"2048-3D"},{"id":20002,"title":"Simon Stalenhag’s flooded paintings"},{"id":20001,"title":"Twisted nightmares from Anatoly Fomenko"},{"id":30005,"title":"Thesis: Topology, Lost Chapters"},{"id":30004,"title":"2D vector fields with CPU particle tracing"},{"id":30003,"title":"Spearman’s correlation formula"},{"id":30002,"title":"JavaScript Quines"},{"id":30001,"title":"Example code"},{"id":40003,"title":"Values are everywhere"},{"id":40002,"title":"What does it take to do science?"},{"id":40001,"title":"Quailing qualia"}]